{
    "final_name": "Venturi_Nozzle_DN50",
    "final_shape": "Venturi Flow Nozzle",
    "units": "mm",
    "_template_category": "fluid_power",
    "_editable_parameters": {
        "inlet_diameter": 50,
        "throat_diameter": 25,
        "outlet_diameter": 50,
        "convergent_length": 30,
        "throat_length": 15,
        "divergent_length": 60,
        "wall_thickness": 5,
        "flange_outer_diameter": 80,
        "flange_thickness": 10,
        "num_flange_bolts": 4,
        "bolt_hole_diameter": 10,
        "bolt_circle_diameter": 65,
        "tap_hole_diameter": 3,
        "tap_hole_depth": 8
    },
    "_engineering_note": "Classical Venturi tube per ISO 5167. 21-degree convergent cone, cylindrical throat, 7-degree divergent cone. Pressure taps at inlet and throat for differential pressure flow measurement. Flanged ends for pipe connection. Low permanent pressure loss (~10-15%).",
    "parts": {
        "part_1": {
            "coordinate_system": {
                "Euler Angles": [0.0, 0.0, 0.0],
                "Translation Vector": [0.0, 0.0, 0.0]
            },
            "revolve_profile": {
                "face_1": {
                    "loop_1": {
                        "line_1": {
                            "Start Point": [25.0, 0.0],
                            "End Point": [30.0, 0.0]
                        },
                        "line_2": {
                            "Start Point": [30.0, 0.0],
                            "End Point": [30.0, 10.0]
                        },
                        "line_3": {
                            "Start Point": [30.0, 10.0],
                            "End Point": [17.5, 40.0]
                        },
                        "line_4": {
                            "Start Point": [17.5, 40.0],
                            "End Point": [17.5, 55.0]
                        },
                        "line_5": {
                            "Start Point": [17.5, 55.0],
                            "End Point": [30.0, 115.0]
                        },
                        "line_6": {
                            "Start Point": [30.0, 115.0],
                            "End Point": [30.0, 125.0]
                        },
                        "line_7": {
                            "Start Point": [30.0, 125.0],
                            "End Point": [25.0, 125.0]
                        },
                        "line_8": {
                            "Start Point": [25.0, 125.0],
                            "End Point": [25.0, 115.0]
                        },
                        "line_9": {
                            "Start Point": [25.0, 115.0],
                            "End Point": [12.5, 55.0]
                        },
                        "line_10": {
                            "Start Point": [12.5, 55.0],
                            "End Point": [12.5, 40.0]
                        },
                        "line_11": {
                            "Start Point": [12.5, 40.0],
                            "End Point": [25.0, 10.0]
                        },
                        "line_12": {
                            "Start Point": [25.0, 10.0],
                            "End Point": [25.0, 0.0]
                        }
                    }
                }
            },
            "revolve": {
                "axis_origin": [0.0, 0.0],
                "axis_direction": [0.0, 1.0],
                "angle": 360.0,
                "operation": "NewBodyFeatureOperation"
            },
            "description": {
                "name": "Venturi_Body",
                "shape": "Revolved Venturi Tube Profile",
                "length": 60.0,
                "width": 60.0,
                "height": 125.0
            }
        },
        "part_2": {
            "coordinate_system": {
                "Euler Angles": [0.0, 0.0, 0.0],
                "Translation Vector": [0.0, 0.0, 0.0]
            },
            "sketch": {
                "face_1": {
                    "loop_1": {
                        "circle_1": {
                            "Center": [0.0, 0.0],
                            "Radius": 40.0
                        }
                    }
                }
            },
            "extrusion": {
                "extrude_depth_towards_normal": 10.0,
                "extrude_depth_opposite_normal": 0.0,
                "sketch_scale": 1.0,
                "operation": "JoinFeatureOperation"
            },
            "description": {
                "name": "Inlet_Flange",
                "shape": "Circular Inlet Flange",
                "length": 80.0,
                "width": 80.0,
                "height": 10.0
            }
        },
        "part_3": {
            "coordinate_system": {
                "Euler Angles": [0.0, 0.0, 0.0],
                "Translation Vector": [0.0, 0.0, 115.0]
            },
            "sketch": {
                "face_1": {
                    "loop_1": {
                        "circle_1": {
                            "Center": [0.0, 0.0],
                            "Radius": 40.0
                        }
                    }
                }
            },
            "extrusion": {
                "extrude_depth_towards_normal": 10.0,
                "extrude_depth_opposite_normal": 0.0,
                "sketch_scale": 1.0,
                "operation": "JoinFeatureOperation"
            },
            "description": {
                "name": "Outlet_Flange",
                "shape": "Circular Outlet Flange",
                "length": 80.0,
                "width": 80.0,
                "height": 10.0
            }
        },
        "part_4": {
            "coordinate_system": {
                "Euler Angles": [0.0, 0.0, 0.0],
                "Translation Vector": [32.5, 0.0, 0.0]
            },
            "hole_feature": {
                "hole_type": "through",
                "diameter": 10.0,
                "depth": 10.0,
                "direction": [0.0, 0.0, 1.0]
            },
            "pattern": {
                "type": "polar",
                "count": 4,
                "center": [0.0, 0.0, 0.0],
                "total_angle": 360,
                "axis": [0.0, 0.0, 1.0]
            },
            "description": {
                "name": "Inlet_Flange_Bolt_Holes",
                "shape": "Through Bolt Holes (4x M10)",
                "length": 10.0,
                "width": 10.0,
                "height": 10.0
            }
        },
        "part_5": {
            "coordinate_system": {
                "Euler Angles": [0.0, 0.0, 0.0],
                "Translation Vector": [32.5, 0.0, 115.0]
            },
            "hole_feature": {
                "hole_type": "through",
                "diameter": 10.0,
                "depth": 10.0,
                "direction": [0.0, 0.0, 1.0]
            },
            "pattern": {
                "type": "polar",
                "count": 4,
                "center": [0.0, 0.0, 115.0],
                "total_angle": 360,
                "axis": [0.0, 0.0, 1.0]
            },
            "description": {
                "name": "Outlet_Flange_Bolt_Holes",
                "shape": "Through Bolt Holes (4x M10)",
                "length": 10.0,
                "width": 10.0,
                "height": 10.0
            }
        },
        "part_6": {
            "coordinate_system": {
                "Euler Angles": [0.0, 0.0, 0.0],
                "Translation Vector": [30.0, 0.0, 5.0]
            },
            "hole_feature": {
                "hole_type": "blind",
                "diameter": 3.0,
                "depth": 8.0,
                "direction": [1.0, 0.0, 0.0]
            },
            "description": {
                "name": "Inlet_Pressure_Tap",
                "shape": "Radial Pressure Tap Hole",
                "length": 3.0,
                "width": 3.0,
                "height": 8.0
            }
        },
        "part_7": {
            "coordinate_system": {
                "Euler Angles": [0.0, 0.0, 0.0],
                "Translation Vector": [17.5, 0.0, 47.0]
            },
            "hole_feature": {
                "hole_type": "blind",
                "diameter": 3.0,
                "depth": 5.0,
                "direction": [1.0, 0.0, 0.0]
            },
            "description": {
                "name": "Throat_Pressure_Tap",
                "shape": "Radial Throat Pressure Tap Hole",
                "length": 3.0,
                "width": 3.0,
                "height": 5.0
            }
        }
    }
}
